DNApy/__init__.py
DNApy/clustering.py
DNApy/common.py
DNApy/foo.py
DNApy/parsers.py
dnapy-0.1.2.1.dist-info/licenses/LICENSE.txt
dnapy-0.1.2.1.dist-info/METADATA
dnapy-0.1.2.1.dist-info/WHEEL
dnapy-0.1.2.1.dist-info/top_level.txt
dnapy-0.1.2.1.dist-info/RECORD
